ccfkotlin/__init__.py
ccfkotlin/__main__.py
ccfkotlin/ccf.py
ccfkotlin/dfaMatchers.py
ccfkotlin/l_token.py
ccfkotlin/lexer.py
ccfkotlin/regexMatchers.py
ccfkotlin/utils.py
ccfkotlin-1.1.0.dist-info/METADATA
ccfkotlin-1.1.0.dist-info/WHEEL
ccfkotlin-1.1.0.dist-info/entry_points.txt
ccfkotlin-1.1.0.dist-info/top_level.txt
ccfkotlin-1.1.0.dist-info/RECORD
