Metadata-Version: 2.1
Name: ccfkotlin
Version: 1.1.0
Summary: Kotlin code conversions fixer
Home-page: https://github.com/alexandrakmet/Metaprogramming
Author: Alexandra Kmet
License: UNKNOWN
Platform: UNKNOWN
